Metadata-Version: 2.4
Name: monocle_apptrace
Version: 0.7.2
Summary: package with monocle genAI tracing
Project-URL: Homepage, https://github.com/monocle2ai/monocle
Project-URL: Issues, https://github.com/monocle2ai/monocle/issues
Author-email: "Okahu Inc." <okahu-pypi@okahu.ai>
License: Apache-2.0
License-File: LICENSE
Classifier: License :: OSI Approved :: Apache Software License
Classifier: Operating System :: OS Independent
Classifier: Programming Language :: Python :: 3
Requires-Python: >=3.8
Requires-Dist: opentelemetry-api
Requires-Dist: opentelemetry-instrumentation
Requires-Dist: opentelemetry-sdk
Requires-Dist: requests
Requires-Dist: rfc3986>=2.0.0
Requires-Dist: wrapt>=1.14.0
Provides-Extra: ai-test
Requires-Dist: bert-score; extra == 'ai-test'
Requires-Dist: transformers; extra == 'ai-test'
Provides-Extra: aws
Requires-Dist: boto3==1.37.24; extra == 'aws'
Provides-Extra: azure
Requires-Dist: azure-ai-inference; extra == 'azure'
Requires-Dist: azure-storage-blob==12.22.0; extra == 'azure'
Provides-Extra: dev
Requires-Dist: a2a-sdk==0.3.6; extra == 'dev'
Requires-Dist: anthropic-haystack==4.6.0; extra == 'dev'
Requires-Dist: anthropic==0.57.1; extra == 'dev'
Requires-Dist: azure-storage-blob==12.22.0; extra == 'dev'
Requires-Dist: boto3==1.39.0; extra == 'dev'
Requires-Dist: chromadb==1.0.15; extra == 'dev'
Requires-Dist: click==8.2.1; extra == 'dev'
Requires-Dist: crewai==0.95.0; extra == 'dev'
Requires-Dist: datasets==4.3.0; extra == 'dev'
Requires-Dist: faiss-cpu==1.8.0; extra == 'dev'
Requires-Dist: fastapi>=0.115.0; extra == 'dev'
Requires-Dist: fastmcp==2.14.1; extra == 'dev'
Requires-Dist: flask; extra == 'dev'
Requires-Dist: google-adk; extra == 'dev'
Requires-Dist: google-ai-haystack; extra == 'dev'
Requires-Dist: google-generativeai; extra == 'dev'
Requires-Dist: haystack-ai==2.21.0; extra == 'dev'
Requires-Dist: httpx==0.28.1; extra == 'dev'
Requires-Dist: huggingface-hub==0.35.3; extra == 'dev'
Requires-Dist: instructorembedding==1.0.1; extra == 'dev'
Requires-Dist: langchain-anthropic==0.3.13; extra == 'dev'
Requires-Dist: langchain-aws==0.2.23; extra == 'dev'
Requires-Dist: langchain-chroma==0.2.4; extra == 'dev'
Requires-Dist: langchain-community==0.3.24; extra == 'dev'
Requires-Dist: langchain-google-genai; extra == 'dev'
Requires-Dist: langchain-mcp-adapters==0.1.8; extra == 'dev'
Requires-Dist: langchain-mistralai==0.2.10; extra == 'dev'
Requires-Dist: langchain-openai; extra == 'dev'
Requires-Dist: langchain==0.3.25; extra == 'dev'
Requires-Dist: langchainhub==0.1.21; extra == 'dev'
Requires-Dist: langgraph-supervisor==0.0.28; extra == 'dev'
Requires-Dist: langgraph==0.5.4; extra == 'dev'
Requires-Dist: litellm==1.77.5; extra == 'dev'
Requires-Dist: llama-index-embeddings-huggingface==0.6.0; extra == 'dev'
Requires-Dist: llama-index-llms-anthropic==0.8.1; extra == 'dev'
Requires-Dist: llama-index-llms-azure-openai==0.4.0; extra == 'dev'
Requires-Dist: llama-index-llms-mistralai==0.7.0; extra == 'dev'
Requires-Dist: llama-index-llms-openai==0.5.0; extra == 'dev'
Requires-Dist: llama-index-tools-mcp==0.3.0; extra == 'dev'
Requires-Dist: llama-index-vector-stores-chroma==0.5.0; extra == 'dev'
Requires-Dist: llama-index-vector-stores-opensearch==0.6.0; extra == 'dev'
Requires-Dist: llama-index==0.13.0; extra == 'dev'
Requires-Dist: mcp==1.24.0; extra == 'dev'
Requires-Dist: mistral-haystack==0.0.2; extra == 'dev'
Requires-Dist: mistralai==1.9.9; extra == 'dev'
Requires-Dist: numpy==1.26.4; extra == 'dev'
Requires-Dist: openai-agents; extra == 'dev'
Requires-Dist: opendal==0.45.14; extra == 'dev'
Requires-Dist: opensearch-haystack==1.2.0; extra == 'dev'
Requires-Dist: opentelemetry-instrumentation-flask; extra == 'dev'
Requires-Dist: parameterized==0.9.0; extra == 'dev'
Requires-Dist: pydantic==2.11.7; extra == 'dev'
Requires-Dist: pytest-asyncio==0.26.0; extra == 'dev'
Requires-Dist: pytest-venv; extra == 'dev'
Requires-Dist: pytest==8.3.5; extra == 'dev'
Requires-Dist: python-dotenv>=1.1.0; extra == 'dev'
Requires-Dist: requests-aws4auth==1.2.3; extra == 'dev'
Requires-Dist: types-requests==2.31.0.20240106; extra == 'dev'
Requires-Dist: uvicorn==0.35.0; extra == 'dev'
Provides-Extra: dev-gemini
Requires-Dist: llama-index-llms-gemini==0.6.0; extra == 'dev-gemini'
Provides-Extra: dev-strands
Requires-Dist: strands-agents-tools==0.2.10; extra == 'dev-strands'
Requires-Dist: strands-agents==1.11.0; extra == 'dev-strands'
Provides-Extra: dev-tranformers
Requires-Dist: sentence-transformers==5.2.0; extra == 'dev-tranformers'
Provides-Extra: opentelemetry-exporter
Requires-Dist: opentelemetry-exporter-otlp-proto-http; extra == 'opentelemetry-exporter'
